aiobottle.py
setup.py
aiobottle.egg-info/PKG-INFO
aiobottle.egg-info/SOURCES.txt
aiobottle.egg-info/dependency_links.txt
aiobottle.egg-info/requires.txt
aiobottle.egg-info/top_level.txt