Metadata-Version: 1.0
Name: aiobottle
Version: 0.1.1
Summary: Aiobottle, a warper bottle use aiohttp base on  Asyncio (PEP-3156)
Home-page: https://github.com/Lupino/aiobottle
Author: Li Meng Jun
Author-email: lmjubuntu@gmail.com
License: UNKNOWN
Platform: UNKNOWN
